[
  {
    "inputs": [
      {
        "internalType": "address",
        "name": "_msmilToken",
        "type": "address"
      },
      {
        "internalType": "address",
        "name": "_owner",
        "type": "address"
      },
      {
        "internalType": "address",
        "name": "_feeRecipient",
        "type": "address"
      },
      {
        "internalType": "uint256[]",
        "name": "_supportedChainIds",
        "type": "uint256[]"
      }
    ],
    "stateMutability": "nonpayable",
    "type": "constructor"
  },
  {
    "inputs": [],
    "name": "BridgeToSameChain",
    "type": "error"
  },
  {
    "inputs": [],
    "name": "InvalidAmount",
    "type": "error"
  },
  {
    "inputs": [],
    "name": "InvalidFee",
    "type": "error"
  },
  {
    "inputs": [],
    "name": "TransactionAlreadyProcessed",
    "type": "error"
  },
  {
    "inputs": [],
    "name": "UnauthorizedBridge",
    "type": "error"
  },
  {
    "inputs": [],
    "name": "UnsupportedChain",
    "type": "error"
  },
  {
    "inputs": [],
    "name": "ZeroAddress",
    "type": "error"
  },
  {
    "anonymous": false,
    "inputs": [
      {
        "indexed": true,
        "internalType": "address",
        "name": "user",
        "type": "address"
      },
      {
        "indexed": true,
        "internalType": "uint256",
        "name": "fromChain",
        "type": "uint256"
      },
      {
        "indexed": true,
        "internalType": "uint256",
        "name": "toChain",
        "type": "uint256"
      },
      {
        "indexed": false,
        "internalType": "uint256",
        "name": "amount",
        "type": "uint256"
      },
      {
        "indexed": true,
        "internalType": "bytes32",
        "name": "transactionId",
        "type": "bytes32"
      }
    ],
    "name": "BridgeCompleted",
    "type": "event"
  },
  {
    "anonymous": false,
    "inputs": [
      {
        "indexed": false,
        "internalType": "uint256",
        "name": "newFee",
        "type": "uint256"
      }
    ],
    "name": "BridgeFeeUpdated",
    "type": "event"
  },
  {
    "anonymous": false,
    "inputs": [
      {
        "indexed": true,
        "internalType": "address",
        "name": "user",
        "type": "address"
      },
      {
        "indexed": true,
        "internalType": "uint256",
        "name": "fromChain",
        "type": "uint256"
      },
      {
        "indexed": true,
        "internalType": "uint256",
        "name": "toChain",
        "type": "uint256"
      },
      {
        "indexed": false,
        "internalType": "uint256",
        "name": "amount",
        "type": "uint256"
      },
      {
        "indexed": false,
        "internalType": "uint256",
        "name": "fee",
        "type": "uint256"
      },
      {
        "indexed": false,
        "internalType": "uint256",
        "name": "nonce",
        "type": "uint256"
      },
      {
        "indexed": false,
        "internalType": "bytes32",
        "name": "transactionId",
        "type": "bytes32"
      }
    ],
    "name": "BridgeInitiated",
    "type": "event"
  },
  {
    "anonymous": false,
    "inputs": [
      {
        "indexed": false,
        "internalType": "uint256",
        "name": "newMinAmount",
        "type": "uint256"
      },
      {
        "indexed": false,
        "internalType": "uint256",
        "name": "newMaxAmount",
        "type": "uint256"
      }
    ],
    "name": "BridgeLimitsUpdated",
    "type": "event"
  },
  {
    "anonymous": false,
    "inputs": [
      {
        "indexed": true,
        "internalType": "uint256",
        "name": "chainId",
        "type": "uint256"
      },
      {
        "indexed": false,
        "internalType": "uint256",
        "name": "newFee",
        "type": "uint256"
      }
    ],
    "name": "ChainBridgeFeeUpdated",
    "type": "event"
  },
  {
    "anonymous": false,
    "inputs": [
      {
        "indexed": true,
        "internalType": "uint256",
        "name": "chainId",
        "type": "uint256"
      },
      {
        "indexed": false,
        "internalType": "bool",
        "name": "supported",
        "type": "bool"
      }
    ],
    "name": "ChainSupported",
    "type": "event"
  },
  {
    "anonymous": false,
    "inputs": [
      {
        "indexed": true,
        "internalType": "address",
        "name": "newRecipient",
        "type": "address"
      }
    ],
    "name": "FeeRecipientUpdated",
    "type": "event"
  },
  {
    "anonymous": false,
    "inputs": [
      {
        "indexed": true,
        "internalType": "address",
        "name": "recipient",
        "type": "address"
      },
      {
        "indexed": false,
        "internalType": "uint256",
        "name": "amount",
        "type": "uint256"
      }
    ],
    "name": "FeesWithdrawn",
    "type": "event"
  },
  {
    "inputs": [],
    "name": "MAX_FEE",
    "outputs": [
      {
        "internalType": "uint256",
        "name": "",
        "type": "uint256"
      }
    ],
    "stateMutability": "view",
    "type": "function"
  },
  {
    "inputs": [],
    "name": "MIN_FEE",
    "outputs": [
      {
        "internalType": "uint256",
        "name": "",
        "type": "uint256"
      }
    ],
    "stateMutability": "view",
    "type": "function"
  },
  {
    "inputs": [],
    "name": "bridgeFee",
    "outputs": [
      {
        "internalType": "uint256",
        "name": "",
        "type": "uint256"
      }
    ],
    "stateMutability": "view",
    "type": "function"
  },
  {
    "inputs": [
      {
        "internalType": "uint256",
        "name": "toChain",
        "type": "uint256"
      },
      {
        "internalType": "uint256",
        "name": "amount",
        "type": "uint256"
      },
      {
        "internalType": "address",
        "name": "recipient",
        "type": "address"
      }
    ],
    "name": "bridgeTokens",
    "outputs": [],
    "stateMutability": "nonpayable",
    "type": "function"
  },
  {
    "inputs": [
      {
        "internalType": "uint256",
        "name": "",
        "type": "uint256"
      }
    ],
    "name": "chainBridgeFees",
    "outputs": [
      {
        "internalType": "uint256",
        "name": "",
        "type": "uint256"
      }
    ],
    "stateMutability": "view",
    "type": "function"
  },
  {
    "inputs": [],
    "name": "collectedFees",
    "outputs": [
      {
        "internalType": "uint256",
        "name": "",
        "type": "uint256"
      }
    ],
    "stateMutability": "view",
    "type": "function"
  },
  {
    "inputs": [
      {
        "internalType": "address",
        "name": "user",
        "type": "address"
      },
      {
        "internalType": "address",
        "name": "recipient",
        "type": "address"
      },
      {
        "internalType": "uint256",
        "name": "amount",
        "type": "uint256"
      },
      {
        "internalType": "uint256",
        "name": "fromChain",
        "type": "uint256"
      },
      {
        "internalType": "bytes32",
        "name": "transactionId",
        "type": "bytes32"
      }
    ],
    "name": "completeBridge",
    "outputs": [],
    "stateMutability": "nonpayable",
    "type": "function"
  },
  {
    "inputs": [],
    "name": "feeRecipient",
    "outputs": [
      {
        "internalType": "address",
        "name": "",
        "type": "address"
      }
    ],
    "stateMutability": "view",
    "type": "function"
  },
  {
    "inputs": [
      {
        "internalType": "uint256",
        "name": "toChain",
        "type": "uint256"
      },
      {
        "internalType": "uint256",
        "name": "amount",
        "type": "uint256"
      }
    ],
    "name": "getBridgeFee",
    "outputs": [
      {
        "internalType": "uint256",
        "name": "",
        "type": "uint256"
      }
    ],
    "stateMutability": "view",
    "type": "function"
  },
  {
    "inputs": [
      {
        "internalType": "uint256",
        "name": "toChain",
        "type": "uint256"
      }
    ],
    "name": "getBridgeFeePercentage",
    "outputs": [
      {
        "internalType": "string",
        "name": "",
        "type": "string"
      }
    ],
    "stateMutability": "view",
    "type": "function"
  },
  {
    "inputs": [
      {
        "internalType": "uint256",
        "name": "toChain",
        "type": "uint256"
      }
    ],
    "name": "getBridgeFeeRate",
    "outputs": [
      {
        "internalType": "uint256",
        "name": "",
        "type": "uint256"
      }
    ],
    "stateMutability": "view",
    "type": "function"
  },
  {
    "inputs": [],
    "name": "getBridgeLimits",
    "outputs": [
      {
        "internalType": "uint256",
        "name": "min",
        "type": "uint256"
      },
      {
        "internalType": "uint256",
        "name": "max",
        "type": "uint256"
      }
    ],
    "stateMutability": "view",
    "type": "function"
  },
  {
    "inputs": [
      {
        "internalType": "address",
        "name": "user",
        "type": "address"
      }
    ],
    "name": "getUserNonce",
    "outputs": [
      {
        "internalType": "uint256",
        "name": "",
        "type": "uint256"
      }
    ],
    "stateMutability": "view",
    "type": "function"
  },
  {
    "inputs": [
      {
        "internalType": "bytes32",
        "name": "transactionId",
        "type": "bytes32"
      }
    ],
    "name": "isTransactionProcessed",
    "outputs": [
      {
        "internalType": "bool",
        "name": "",
        "type": "bool"
      }
    ],
    "stateMutability": "view",
    "type": "function"
  },
  {
    "inputs": [],
    "name": "maxBridgeAmount",
    "outputs": [
      {
        "internalType": "uint256",
        "name": "",
        "type": "uint256"
      }
    ],
    "stateMutability": "view",
    "type": "function"
  },
  {
    "inputs": [],
    "name": "minBridgeAmount",
    "outputs": [
      {
        "internalType": "uint256",
        "name": "",
        "type": "uint256"
      }
    ],
    "stateMutability": "view",
    "type": "function"
  },
  {
    "inputs": [],
    "name": "msmilToken",
    "outputs": [
      {
        "internalType": "contract IMilestoneMillions",
        "name": "",
        "type": "address"
      }
    ],
    "stateMutability": "view",
    "type": "function"
  },
  {
    "inputs": [],
    "name": "pause",
    "outputs": [],
    "stateMutability": "nonpayable",
    "type": "function"
  },
  {
    "inputs": [
      {
        "internalType": "uint256",
        "name": "",
        "type": "uint256"
      }
    ],
    "name": "processedTransactions",
    "outputs": [
      {
        "internalType": "bool",
        "name": "",
        "type": "bool"
      }
    ],
    "stateMutability": "view",
    "type": "function"
  },
  {
    "inputs": [
      {
        "internalType": "uint256",
        "name": "_bridgeFee",
        "type": "uint256"
      }
    ],
    "name": "setBridgeFee",
    "outputs": [],
    "stateMutability": "nonpayable",
    "type": "function"
  },
  {
    "inputs": [
      {
        "internalType": "uint256",
        "name": "_minBridgeAmount",
        "type": "uint256"
      },
      {
        "internalType": "uint256",
        "name": "_maxBridgeAmount",
        "type": "uint256"
      }
    ],
    "name": "setBridgeLimits",
    "outputs": [],
    "stateMutability": "nonpayable",
    "type": "function"
  },
  {
    "inputs": [
      {
        "internalType": "uint256",
        "name": "chainId",
        "type": "uint256"
      },
      {
        "internalType": "uint256",
        "name": "_bridgeFee",
        "type": "uint256"
      }
    ],
    "name": "setChainBridgeFee",
    "outputs": [],
    "stateMutability": "nonpayable",
    "type": "function"
  },
  {
    "inputs": [
      {
        "internalType": "address",
        "name": "_feeRecipient",
        "type": "address"
      }
    ],
    "name": "setFeeRecipient",
    "outputs": [],
    "stateMutability": "nonpayable",
    "type": "function"
  },
  {
    "inputs": [
      {
        "internalType": "uint256",
        "name": "chainId",
        "type": "uint256"
      },
      {
        "internalType": "bool",
        "name": "supported",
        "type": "bool"
      }
    ],
    "name": "setSupportedChain",
    "outputs": [],
    "stateMutability": "nonpayable",
    "type": "function"
  },
  {
    "inputs": [
      {
        "internalType": "uint256",
        "name": "",
        "type": "uint256"
      }
    ],
    "name": "supportedChains",
    "outputs": [
      {
        "internalType": "bool",
        "name": "",
        "type": "bool"
      }
    ],
    "stateMutability": "view",
    "type": "function"
  },
  {
    "inputs": [],
    "name": "unpause",
    "outputs": [],
    "stateMutability": "nonpayable",
    "type": "function"
  },
  {
    "inputs": [
      {
        "internalType": "address",
        "name": "",
        "type": "address"
      }
    ],
    "name": "userNonce",
    "outputs": [
      {
        "internalType": "uint256",
        "name": "",
        "type": "uint256"
      }
    ],
    "stateMutability": "view",
    "type": "function"
  }
]